Workbook

Sheet Summary
A1: Mini ERP: Sales & Inventory Summary
A3: Total Revenue | B3: =SUM(Sales_Detail!I2:I150) -> 2442062
A4: Units Sold | B4: =SUM(Sales_Detail!G2:G150) -> 856
A5: Order Lines | B5: =COUNT(Sales_Detail!A2:A150) -> 149
A6: Inventory Value (at cost) | B6: =SUM(Inventory!H2:H21) -> 942940
A7: Products to Reorder | B7: =COUNTIF(Inventory!I2:I21,"REORDER") -> 4
A8: Top Product by Revenue | B8: =INDEX(Sales_By_Product!A2:A21,MATCH(MAX(Sales_By_Product!C2:C21),Sales_By_Product!C2:C21,0)) -> 27-inch Monitor
A9: Best Month by Revenue | B9: =INDEX(Monthly_Sales!A2:A10,MATCH(MAX(Monthly_Sales!B2:B10),Monthly_Sales!B2:B10,0)) -> 2026-05
A11: Note: all figures are formulas over the Sales_Detail and Inventory sheets (data exported from MySQL). Amounts in INR.

Sheet Sales_Detail
A1: Order ID | B1: Order Date | C1: Month | D1: Customer | E1: Product | F1: Category | G1: Qty | H1: Unit Price | I1: Line Total
A2: 37 | B2: 2026-01-03 | C2: 2026-01 | D2: Jupiter Textiles | E2: Webcam HD | F2: Electronics | G2: 8 | H2: 1899 | I2: =G2*H2 -> 15192
A3: 37 | B3: 2026-01-03 | C3: 2026-01 | D3: Jupiter Textiles | E3: Laptop Stand | F3: Electronics | G3: 10 | H3: 999 | I3: =G3*H3 -> 9990
A4: 63 | B4: 2026-01-03 | C4: 2026-01 | D4: Metro Auto Parts | E4: Laptop Stand | F4: Electronics | G4: 7 | H4: 999 | I4: =G4*H4 -> 6993
A5: 56 | B5: 2026-01-10 | C5: 2026-01 | D5: FreshMart Retail | E5: Wireless Mouse | F5: Electronics | G5: 1 | H5: 599 | I5: =G5*H5 -> 599
A6: 24 | B6: 2026-01-14 | C6: 2026-01 | D6: InnoSoft Systems | E6: USB-C Hub | F6: Electronics | G6: 6 | H6: 1499 | I6: =G6*H6 -> 8994
A7: 24 | B7: 2026-01-14 | C7: 2026-01 | D7: InnoSoft Systems | E7: Filing Cabinet | F7: Furniture | G7: 2 | H7: 5499 | I7: =G7*H7 -> 10998
A8: 24 | B8: 2026-01-14 | C8: 2026-01 | D8: InnoSoft Systems | E8: Inkjet Cartridge | F8: Printing | G8: 6 | H8: 1099 | I8: =G8*H8 -> 6594
A9: 32 | B9: 2026-01-15 | C9: 2026-01 | D9: CityCare Clinics | E9: Laptop Stand | F9: Electronics | G9: 9 | H9: 999 | I9: =G9*H9 -> 8991
A10: 32 | B10: 2026-01-15 | C10: 2026-01 | D10: CityCare Clinics | E10: Printer Toner | F10: Printing | G10: 9 | H10: 3499 | I10: =G10*H10 -> 31491
A11: 32 | B11: 2026-01-15 | C11: 2026-01 | D11: CityCare Clinics | E11: Ball Pen Box (50) | F11: Stationery | G11: 3 | H11: 249 | I11: =G11*H11 -> 747
A12: 32 | B12: 2026-01-15 | C12: 2026-01 | D12: CityCare Clinics | E12: Surge Protector | F12: Electronics | G12: 1 | H12: 749 | I12: =G12*H12 -> 749
A13: 40 | B13: 2026-01-15 | C13: 2026-01 | D13: Horizon Realty | E13: Whiteboard Marker Set | F13: Stationery | G13: 6 | H13: 229 | I13: =G13*H13 -> 1374
... A150: 42 | B150: 2026-09-25 | C150: 2026-09 | D150: Lotus Hospitality | E150: Laptop Stand | F150: Electronics | G150: 2 | H150: 999 | I150: =G150*H150 -> 1998

Sheet Inventory
A1: Product ID | B1: SKU | C1: Product | D1: Supplier | E1: Stock Qty | F1: Reorder Level | G1: Unit Cost | H1: Stock Value | I1: Status
A2: 1 | B2: SKU-001 | C2: Wireless Mouse | D2: Nova Peripherals | E2: 120 | F2: 30 | G2: 350 | H2: =E2*G2 -> 42000 | I2: =IF(E2<=F2,"REORDER","OK") -> OK
A3: 2 | B3: SKU-002 | C3: Mechanical Keyboard | D3: Nova Peripherals | E3: 45 | F3: 15 | G3: 1800 | H3: =E3*G3 -> 81000 | I3: =IF(E3<=F3,"REORDER","OK") -> OK
A4: 3 | B4: SKU-003 | C4: USB-C Hub | D4: Delta Electronics | E4: 60 | F4: 20 | G4: 900 | H4: =E4*G4 -> 54000 | I4: =IF(E4<=F4,"REORDER","OK") -> OK
A5: 4 | B5: SKU-004 | C5: 27-inch Monitor | D5: Delta Electronics | E5: 18 | F5: 10 | G5: 9500 | H5: =E5*G5 -> 171000 | I5: =IF(E5<=F5,"REORDER","OK") -> OK
A6: 5 | B6: SKU-005 | C6: Laptop Stand | D6: Delta Electronics | E6: 8 | F6: 15 | G6: 600 | H6: =E6*G6 -> 4800 | I6: =IF(E6<=F6,"REORDER","OK") -> REORDER
A7: 6 | B7: SKU-006 | C7: Webcam HD | D7: Nova Peripherals | E7: 25 | F7: 10 | G7: 1200 | H7: =E7*G7 -> 30000 | I7: =IF(E7<=F7,"REORDER","OK") -> OK
A8: 7 | B8: SKU-007 | C8: Ergonomic Chair | D8: Urban Furnishings | E8: 12 | F8: 8 | G8: 5200 | H8: =E8*G8 -> 62400 | I8: =IF(E8<=F8,"REORDER","OK") -> OK
A9: 8 | B9: SKU-008 | C9: Office Desk | D9: Urban Furnishings | E9: 6 | F9: 8 | G9: 6500 | H9: =E9*G9 -> 39000 | I9: =IF(E9<=F9,"REORDER","OK") -> REORDER
A10: 9 | B10: SKU-009 | C10: Filing Cabinet | D10: Urban Furnishings | E10: 14 | F10: 5 | G10: 3800 | H10: =E10*G10 -> 53200 | I10: =IF(E10<=F10,"REORDER","OK") -> OK
A11: 10 | B11: SKU-010 | C11: Monitor Arm | D11: Urban Furnishings | E11: 22 | F11: 10 | G11: 1500 | H11: =E11*G11 -> 33000 | I11: =IF(E11<=F11,"REORDER","OK") -> OK
A12: 11 | B12: SKU-011 | C12: A4 Paper Ream | D12: Prime Office Supplies | E12: 400 | F12: 100 | G12: 210 | H12: =E12*G12 -> 84000 | I12: =IF(E12<=F12,"REORDER","OK") -> OK
A13: 12 | B13: SKU-012 | C13: Ball Pen Box (50) | D13: Paper & Pen Co. | E13: 150 | F13: 40 | G13: 150 | H13: =E13*G13 -> 22500 | I13: =IF(E13<=F13,"REORDER","OK") -> OK
... A21: 20 | B21: SKU-020 | C21: Surge Protector | D21: Nova Peripherals | E21: 48 | F21: 15 | G21: 450 | H21: =E21*G21 -> 21600 | I21: =IF(E21<=F21,"REORDER","OK") -> OK

Sheet Sales_By_Product
A1: Product | B1: Units Sold | C1: Revenue
A2: 27-inch Monitor | B2: =SUMIFS(Sales_Detail!$G$2:$G$150,Sales_Detail!$E$2:$E$150,A2) -> 64 | C2: =SUMIFS(Sales_Detail!$I$2:$I$150,Sales_Detail!$E$2:$E$150,A2) -> 895936
A3: External SSD 1TB | B3: =SUMIFS(Sales_Detail!$G$2:$G$150,Sales_Detail!$E$2:$E$150,A3) -> 55 | C3: =SUMIFS(Sales_Detail!$I$2:$I$150,Sales_Detail!$E$2:$E$150,A3) -> 412445
A4: Office Desk | B4: =SUMIFS(Sales_Detail!$G$2:$G$150,Sales_Detail!$E$2:$E$150,A4) -> 23 | C4: =SUMIFS(Sales_Detail!$I$2:$I$150,Sales_Detail!$E$2:$E$150,A4) -> 218477
A5: Mechanical Keyboard | B5: =SUMIFS(Sales_Detail!$G$2:$G$150,Sales_Detail!$E$2:$E$150,A5) -> 57 | C5: =SUMIFS(Sales_Detail!$I$2:$I$150,Sales_Detail!$E$2:$E$150,A5) -> 159543
A6: Printer Toner | B6: =SUMIFS(Sales_Detail!$G$2:$G$150,Sales_Detail!$E$2:$E$150,A6) -> 41 | C6: =SUMIFS(Sales_Detail!$I$2:$I$150,Sales_Detail!$E$2:$E$150,A6) -> 143459
A7: Webcam HD | B7: =SUMIFS(Sales_Detail!$G$2:$G$150,Sales_Detail!$E$2:$E$150,A7) -> 57 | C7: =SUMIFS(Sales_Detail!$I$2:$I$150,Sales_Detail!$E$2:$E$150,A7) -> 108243
A8: Ergonomic Chair | B8: =SUMIFS(Sales_Detail!$G$2:$G$150,Sales_Detail!$E$2:$E$150,A8) -> 10 | C8: =SUMIFS(Sales_Detail!$I$2:$I$150,Sales_Detail!$E$2:$E$150,A8) -> 79990
A9: Laptop Stand | B9: =SUMIFS(Sales_Detail!$G$2:$G$150,Sales_Detail!$E$2:$E$150,A9) -> 75 | C9: =SUMIFS(Sales_Detail!$I$2:$I$150,Sales_Detail!$E$2:$E$150,A9) -> 74925
A10: Filing Cabinet | B10: =SUMIFS(Sales_Detail!$G$2:$G$150,Sales_Detail!$E$2:$E$150,A10) -> 13 | C10: =SUMIFS(Sales_Detail!$I$2:$I$150,Sales_Detail!$E$2:$E$150,A10) -> 71487
A11: Inkjet Cartridge | B11: =SUMIFS(Sales_Detail!$G$2:$G$150,Sales_Detail!$E$2:$E$150,A11) -> 65 | C11: =SUMIFS(Sales_Detail!$I$2:$I$150,Sales_Detail!$E$2:$E$150,A11) -> 71435
A12: USB-C Hub | B12: =SUMIFS(Sales_Detail!$G$2:$G$150,Sales_Detail!$E$2:$E$150,A12) -> 47 | C12: =SUMIFS(Sales_Detail!$I$2:$I$150,Sales_Detail!$E$2:$E$150,A12) -> 70453
A13: Label Printer Rolls | B13: =SUMIFS(Sales_Detail!$G$2:$G$150,Sales_Detail!$E$2:$E$150,A13) -> 56 | C13: =SUMIFS(Sales_Detail!$I$2:$I$150,Sales_Detail!$E$2:$E$150,A13) -> 27944
... A21: Stapler | B21: =SUMIFS(Sales_Detail!$G$2:$G$150,Sales_Detail!$E$2:$E$150,A21) -> 43 | C21: =SUMIFS(Sales_Detail!$I$2:$I$150,Sales_Detail!$E$2:$E$150,A21) -> 8557

Sheet Monthly_Sales
A1: Month | B1: Revenue
A2: 2026-01 | B2: =SUMIFS(Sales_Detail!$I$2:$I$150,Sales_Detail!$C$2:$C$150,A2) -> 297484
A3: 2026-02 | B3: =SUMIFS(Sales_Detail!$I$2:$I$150,Sales_Detail!$C$2:$C$150,A3) -> 352750
A4: 2026-03 | B4: =SUMIFS(Sales_Detail!$I$2:$I$150,Sales_Detail!$C$2:$C$150,A4) -> 289846
A5: 2026-04 | B5: =SUMIFS(Sales_Detail!$I$2:$I$150,Sales_Detail!$C$2:$C$150,A5) -> 211728
A6: 2026-05 | B6: =SUMIFS(Sales_Detail!$I$2:$I$150,Sales_Detail!$C$2:$C$150,A6) -> 511344
A7: 2026-06 | B7: =SUMIFS(Sales_Detail!$I$2:$I$150,Sales_Detail!$C$2:$C$150,A7) -> 15584
A8: 2026-07 | B8: =SUMIFS(Sales_Detail!$I$2:$I$150,Sales_Detail!$C$2:$C$150,A8) -> 133439
A9: 2026-08 | B9: =SUMIFS(Sales_Detail!$I$2:$I$150,Sales_Detail!$C$2:$C$150,A9) -> 147173
A10: 2026-09 | B10: =SUMIFS(Sales_Detail!$I$2:$I$150,Sales_Detail!$C$2:$C$150,A10) -> 482714
